[{"name": "ROG Strix G10DK G10DK-AB764 Gaming PC", "price": "649.99", "specs": {"SKU": "556977", "Mfr Part#": "90PF02S2-M00HW0", "UPC": "195553700559", "Subcategory": ["PC Desktops", "Gaming PCs"], "Series": "ROG", "Model Number": "90PF02S2-M00HW0", "Color": "Gray", "Expandability": "Memory", "Operating System": "Windows 11 Home", "Case Orientation": "Vertical", "Chipset": "AMD B550", "CPU Summary": "AMD Ryzen 7 3700X (3.6GHz)", "CPU Core": "Matisse", "CPU Socket": "AM4", "Level 3 Cache": "32MB", "Turbo Boost Speed": "Up to 4.4GHz", "Cores": "Eight-Core", "Total Memory": "16GB", "Memory Configuration": "2 x 8GB", "Maximum Memory Supported": "64GB", "SSD Interface": "PCIe", "SSD Capacity": "512GB", "Display Type": "Display Not Included", "Webcam": "No", "GPU Type": "NVIDIA GeForce GTX 1660 Ti", "Video Memory": "6GB DDR6", "Audio System": "High Definition Audio", "Audio Channels": "7.1", "LAN": "Gigabit LAN", "LAN Data Rate Speed": "10/100/1000Mbps", "WLAN": "2x2 Wi-Fi 5 802.11ac", "Bluetooth": "Bluetooth 5.0", "Wireless Technology": ["802.11a", "802.11b", "802.11g", "WiFi 5 (802.11ac)", "WiFi 4 (802.11n)"], "USB 3.1": ["4 x USB 3.2 (Gen 1 Type-A)", "2 x USB 3.2 (Gen 2 Type-A)"], "Audio": "3", "PS/2": "1", "VGA 15-pin": "1", "DVI": "1", "HDMI": "1", "eSATA 6Gb/s": "4", "LAN RJ-45": "1", "Internal 3.5\" Bays (Total)": "1", "PCIe x16 Slots (Total)": "1", "PCIe x1 Slots (Total)": "1", "M.2": "2", "Keyboard": "USB", "Mouse": "Optical", "Connection Type": "USB", "Power Supply": "500 Watt", "System Security": "Trusted Platform Module 2.0", "Width": "7.09 in. (180.09 mm)", "Weight": "17.64 lbs. (8.00 kg)", "Depth": "16.93 in. (430.02 mm)", "Height": "16.85 in. (428.00 mm)", "What's in the Box": "ROG Strix G10DK G10DK-AB764 Gaming PC, USB Keyboard, USB Mouse", "Preloaded Software": "McAfee Live Safe 30-Day Trial", "Parts": "1 Year Limited", "Labor": "1 Year Limited"}, "images": ["https://www.microcenter.com/endeca/zoomFullScreen.aspx?src=664919_556977_01_front_comping-jpg", "https://www.microcenter.com/endeca/zoomFullScreen.aspx?src=664919_556977_02_front_comping-jpg", "https://www.microcenter.com/endeca/zoomFullScreen.aspx?src=664919_556977_03_front_comping-jpg", "https://www.microcenter.com/endeca/zoomFullScreen.aspx?src=664919_556977_04_front_comping-jpg", "https://www.microcenter.com/endeca/zoomFullScreen.aspx?src=664919_556977_05_front_comping-jpg", "https://www.microcenter.com/endeca/zoomFullScreen.aspx?src=664919_556977_06_front_comping-jpg", "https://www.microcenter.com/endeca/zoomFullScreen.aspx?src=664919_556977_07_package_comping-jpg"], "brand": "ASUS", "category": "Desktop Computers"}]