[{"name": "Vengeance LPX 32GB (2 x 16GB) DDR4-3200 PC4-25600 CL16 Dual Channel Desktop Memory Kit CMK32GX4M2E3200 - Black", "price": "79.99", "specs": {"SKU": "046201", "Mfr Part#": "CMK32GX4M2E3200", "UPC": "840006608547", "Memory Type": "DDR4", "Pin Configuration": "288-pin", "Memory Speed": "PC4-25600", "Memory Speed (MHz)": "DDR4-3200", "Memory Capacity": "32GB (2 x 16GB)", "Memory Channels": "Dual", "Memory Profiles": "Intel XMP", "Number of Modules": "2", "Voltage": "1.35V", "CAS Latency": "16", "Memory Latency Timings": "16-20-20-38", "ECC": "Non-ECC", "Buffered/Unbuffered": "Unbuffered", "Memory Heatsink": "Aluminum Heat Spreader", "LED Color": "None", "What's in the Box": "2 x 16GB Vengeance LPX DDR4-3200 PC4-25600 CL16 Dual Channel Desktop Memory Module - Black", "Parts": "Lifetime Limited", "Labor": "Lifetime Limited"}, "images": ["https://www.microcenter.com/endeca/zoomFullScreen.aspx?src=616299_046201_01_front_comping-jpg", "https://www.microcenter.com/endeca/zoomFullScreen.aspx?src=616299_046201_02_front_comping-jpg", "https://www.microcenter.com/endeca/zoomFullScreen.aspx?src=616299_046201_03_packaging_comping-jpg"], "brand": "Corsair", "category": "Computer Memory"}, {"name": "Ripjaws V 16GB (2 x 8GB) DDR4-3200 PC4-25600 CL16 Dual Channel Desktop Memory Kit F4-3200C16D-16GVKB - Black", "price": "43.99", "specs": {"SKU": "348201", "Mfr Part#": "3200C16D16GVKB", "UPC": "848354014973", "Memory Type": "DDR4", "Pin Configuration": "288-pin", "Memory Speed": "PC4-25600", "Memory Speed (MHz)": "DDR4-3200", "Memory Capacity": "16GB (2 x 8GB)", "Memory Channels": "Dual", "Memory Profiles": "Intel XMP", "Number of Modules": "2", "Voltage": "1.35V", "CAS Latency": "16", "Memory Latency Timings": "16-18-18-38", "ECC": "Non-ECC", "Buffered/Unbuffered": "Unbuffered", "Memory Heatsink": "Heat Spreader", "LED Color": "None", "What's in the Box": "2 x Desktop Memory Module", "Parts": "Lifetime Limited", "Labor": "Lifetime Limited"}, "images": ["https://www.microcenter.com/endeca/zoomFullScreen.aspx?src=481738_348201_01_front_comping-jpg", "https://www.microcenter.com/endeca/zoomFullScreen.aspx?src=481738_348201_02_front_comping-jpg"], "brand": "G.Skill", "category": "Computer Memory"}, {"name": "Ripjaws V 32GB (2 x 16GB) DDR4-3200 PC4-25600 CL16 Dual Channel Desktop Memory Kit F4-3200C16D-32G - Black", "price": "74.99", "specs": {"SKU": "098715", "Mfr Part#": "F4-3200C16D-32G", "UPC": "848354017011", "Memory Type": "DDR4", "Pin Configuration": "288-pin", "Memory Speed": "PC4-25600", "Memory Speed (MHz)": "DDR4-3200", "Memory Capacity": "32GB (2 x 16GB)", "Memory Channels": "Dual", "Memory Profiles": "Intel XMP", "Number of Modules": "2", "Voltage": "1.35V", "CAS Latency": "16", "Memory Latency Timings": "16-18-18-38", "ECC": "Non-ECC", "Buffered/Unbuffered": "Unbuffered", "Memory Heatsink": "Aluminum Heat Spreader", "LED Color": "None", "What's in the Box": "16GB DDR4-3200 PC4-25600 Desktop Memory Modules x2", "Parts": "Lifetime Limited", "Labor": "Lifetime Limited"}, "images": ["https://www.microcenter.com/endeca/zoomFullScreen.aspx?src=467049_098715_01_front_comping-jpg", "https://www.microcenter.com/endeca/zoomFullScreen.aspx?src=467049_098715_02_front_comping-jpg"], "brand": "G.Skill", "category": "Computer Memory"}, {"name": "Vengeance LPX 64GB (2 x 32GB) DDR4-3200 PC4-25600 CL16 Dual Channel Desktop Memory Kit CMK64GX4M2E3200 - Black", "price": "134.99", "specs": {"SKU": "529628", "Mfr Part#": "CMK64GX4M2E3200", "UPC": "840006619208", "Memory Type": "DDR4", "Pin Configuration": "288-pin", "Memory Speed": "PC4-25600", "Memory Speed (MHz)": "DDR4-3200", "Memory Capacity": "64GB (2 x 32GB)", "Memory Channels": "Dual", "Memory Profiles": "Intel XMP", "Number of Modules": "2", "Voltage": "1.35V", "CAS Latency": "16", "Memory Latency Timings": "16-20-20-38", "ECC": "Non-ECC", "Buffered/Unbuffered": "Unbuffered", "Memory Heatsink": "Aluminum Heat Spreader", "LED Color": "None", "Parts": "Lifetime Limited", "Labor": "Lifetime Limited"}, "images": ["https://www.microcenter.com/endeca/zoomFullScreen.aspx?src=661850_529628_01_front_comping-jpg", "https://www.microcenter.com/endeca/zoomFullScreen.aspx?src=661850_529628_02_package_comping-jpg"], "brand": "Corsair", "category": "Computer Memory"}, {"name": "VENGEANCE RGB PRO SL 32GB (2 x 16GB) DDR4-3600 PC4-28800 CL18 Dual Channel Desktop Memory Kit CMH32GX4M2D36KW - White", "price": "84.99", "specs": {"SKU": "233742", "Mfr Part#": "CMH32GX4M2D36KW", "UPC": "840006632085", "Memory Type": "DDR4", "Pin Configuration": "288-pin", "Memory Speed": "PC4-28800", "Memory Speed (MHz)": "DDR4-3600", "Memory Capacity": "32GB (2 x 16GB)", "Memory Channels": "Dual", "Memory Profiles": "Intel XMP", "Number of Modules": "2", "Voltage": "1.35V", "CAS Latency": "18", "Memory Latency Timings": "18-22-22-42", "ECC": "Non-ECC", "Buffered/Unbuffered": "Unbuffered", "Memory Heatsink": "Aluminum Heat Spreader", "LED Color": "RGB Illumination", "What's in the Box": "2 x 16GB VENGEANCE RGB PRO SL DDR4-3600 PC4-28800 CL18 Dual Channel Desktop Memory Module - White", "Parts": "Lifetime Limited", "Labor": "Lifetime Limited"}, "images": ["https://www.microcenter.com/endeca/zoomFullScreen.aspx?src=633118_233742_01_front_comping-jpg", "https://www.microcenter.com/endeca/zoomFullScreen.aspx?src=633118_233742_02_package_comping-jpg"], "brand": "Corsair", "category": "Computer Memory"}, {"name": "Vengeance RGB RT 32GB (2 x 16GB) DDR4-3600 PC4-28800 CL16 Dual Channel Desktop Memory Kit CMN32GX4M2Z3600 - Black", "price": "109.99", "specs": {"SKU": "390633", "Mfr Part#": "CMN32GX4M2Z3600", "UPC": "840006650577", "Memory Type": "DDR4", "Pin Configuration": "288-pin", "Memory Speed": "PC4-28800", "Memory Speed (MHz)": "DDR4-3600", "Memory Capacity": "32GB (2 x 16GB)", "Memory Channels": "Dual", "Memory Profiles": "Intel XMP", "Number of Modules": "2", "Voltage": "1.35V", "CAS Latency": "16", "Memory Latency Timings": "16-20-20-38", "ECC": "Non-ECC", "Buffered/Unbuffered": "Unbuffered", "Memory Heatsink": "Aluminum Heat Spreader", "LED Color": "RGB Illumination", "Parts": "Lifetime Limited", "Labor": "Lifetime Limited"}, "images": ["https://www.microcenter.com/endeca/zoomFullScreen.aspx?src=648419_390633_01_front_comping-jpg", "https://www.microcenter.com/endeca/zoomFullScreen.aspx?src=648419_390633_02_package_comping-jpg"], "brand": "Corsair", "category": "Computer Memory"}, {"name": "T-FORCE VULCAN Z 32GB (2 x 16GB) DDR4-3200 PC4-25600 CL16 Dual Channel Desktop Memory Kit TLZGD432G3200H - Gray", "price": "66.99", "specs": {"SKU": "226266", "Mfr Part#": "TLZGD432G3200H", "UPC": "765441654204", "Memory Type": "DDR4", "Pin Configuration": "288-pin", "Memory Speed": "PC4-25600", "Memory Speed (MHz)": "DDR4-3200", "Memory Capacity": "32GB (2 x 16GB)", "Memory Channels": "Dual", "Memory Profiles": "Intel XMP", "Number of Modules": "2", "Voltage": "1.35V", "CAS Latency": "16", "Memory Latency Timings": "16-20-20-40", "ECC": "Non-ECC", "Buffered/Unbuffered": "Unbuffered", "Memory Heatsink": "Aluminum Heat Spreader", "LED Color": "None", "What's in the Box": "2 x 16GB T-FORCE VULCAN Z DDR4-3200 PC4-25600 CL16 Dual Channel Desktop Memory Module - Gray", "Parts": "Lifetime Limited", "Labor": "Lifetime Limited"}, "images": ["https://www.microcenter.com/endeca/zoomFullScreen.aspx?src=632929_226266_01_front_comping-jpg", "https://www.microcenter.com/endeca/zoomFullScreen.aspx?src=632929_226266_02_front_comping-jpg", "https://www.microcenter.com/endeca/zoomFullScreen.aspx?src=632929_226266_03_front_comping-jpg", "https://www.microcenter.com/endeca/zoomFullScreen.aspx?src=632929_226266_04_package_comping-jpg"], "brand": "TeamGroup", "category": "Computer Memory"}, {"name": "Vengeance LPX 16GB (2 x 8GB) DDR4-3200 C16 Dual Channel Desktop Memory Kit CMK16GX4M2E3200 - Black", "price": "44.99", "specs": {"SKU": "280792", "Mfr Part#": "CMK16GX4M2E3200", "UPC": "840006608530", "Memory Type": "DDR4", "Pin Configuration": "288-pin", "Memory Speed": "PC4-25600", "Memory Speed (MHz)": "DDR4-3200", "Memory Capacity": "16GB (2 x 8GB)", "Memory Channels": "Dual", "Memory Profiles": "Intel XMP", "Number of Modules": "2", "Voltage": "1.35V", "CAS Latency": "16", "Memory Latency Timings": "16-20-20-38", "ECC": "Non-ECC", "Buffered/Unbuffered": "Unbuffered", "Memory Heatsink": "Aluminum Heat Spreader", "LED Color": "None", "Parts": "Lifetime Limited", "Labor": "Lifetime Limited"}, "images": ["https://www.microcenter.com/endeca/zoomFullScreen.aspx?src=637453_280792_01_front_comping-jpg", "https://www.microcenter.com/endeca/zoomFullScreen.aspx?src=637453_280792_02_package_comping-jpg"], "brand": "Corsair", "category": "Computer Memory"}, {"name": "Vengeance RGB Pro 32GB (2 x 16GB) DDR4-3200 PC4-25600 CL16 Dual Channel Desktop Memory Kit CMW32GX4M2E3200C16 - Black", "price": "99.99", "specs": {"SKU": "046177", "Mfr Part#": "CMW32GX4M2E3200", "UPC": "840006613251", "Memory Type": "DDR4", "Pin Configuration": "288-pin", "Memory Speed": "PC4-25600", "Memory Speed (MHz)": "DDR4-3200", "Memory Capacity": "32GB (2 x 16GB)", "Memory Channels": "Dual", "Memory Profiles": "Intel XMP", "Number of Modules": "2", "Voltage": "1.35V", "CAS Latency": "16", "Memory Latency Timings": "16-20-20-38", "ECC": "Non-ECC", "Buffered/Unbuffered": "Unbuffered", "Memory Heatsink": "Aluminum Heat Spreader", "LED Color": "RGB Illumination", "What's in the Box": "2 x 16GB Vengeance RGB Pro DDR4-3200 PC4-25600 CL16 Dual Channel Desktop Memory Module - Black", "Parts": "Lifetime Limited", "Labor": "Lifetime Limited"}, "images": ["https://www.microcenter.com/endeca/zoomFullScreen.aspx?src=616297_046177_01_front_comping-jpg", "https://www.microcenter.com/endeca/zoomFullScreen.aspx?src=616297_046177_02_package_comping-jpg"], "brand": "Corsair", "category": "Computer Memory"}]